{
  "IsEncrypted": false,
  "Values": {
    "AzureWebJobsStorage": "UseDevelopmentStorage=true",
    "FUNCTIONS_WORKER_RUNTIME": "dotnet",
    "RutaLog": "C:\\Log\\",
    "ConectionStringRequest001": "Endpoint=sb://crecoscorpprod.servicebus.windows.net/;SharedAccessKeyName=RootListenSharedAccessKey;SharedAccessKey=cHwMILbcjBXUFWQjugAV9GNT0+kqPiR3QFFxMXVGDmk=",
    "QueueRequest001": "apisac020002queuerequest",
    "UriConsumoWebService": "http://192.168.82.43:82/ProcesosServicioTecnico/",
    "MetodoWsUriConsumowebService": "/api/serviciotecnico/ActualizaRequisicion/",
    "ASPNETCORE_ENVIRONMENT": "SIT",
    "TimeSleep": "1",
    "Attempts": "10"
  }
}